fontman/__init__.py
fontman/_cli.py
fontman/_errors.py
fontman/_install.py
fontman/_list.py
fontman/_remove.py
fontman/_update.py
fontman/tools.py
fontman-0.1.7.dist-info/LICENSE
fontman-0.1.7.dist-info/METADATA
fontman-0.1.7.dist-info/WHEEL
fontman-0.1.7.dist-info/entry_points.txt
fontman-0.1.7.dist-info/top_level.txt
fontman-0.1.7.dist-info/RECORD
