Metadata-Version: 2.2
Name: fontman
Version: 0.1.7
Summary: Manage and update your installed fonts
Author-email: Nico Schlömer <nico.schloemer@gmail.com>
License: The MIT License (MIT)
Project-URL: Code, https://github.com/nschloe/fontman
Project-URL: Funding, https://github.com/sponsors/nschloe
Project-URL: Issues, https://github.com/nschloe/fontman/issues
Classifier: Development Status :: 3 - Alpha
Classifier: Intended Audience :: Science/Research
Classifier: License :: OSI Approved :: MIT License
Classifier: Operating System :: OS Independent
Classifier: Programming Language :: Python
Classifier: Programming Language :: Python :: 3 :: Only
Classifier: Programming Language :: Python :: 3.8
Classifier: Programming Language :: Python :: 3.9
Classifier: Programming Language :: Python :: 3.10
Classifier: Programming Language :: Python :: 3.11
Classifier: Programming Language :: Python :: 3.12
Classifier: Programming Language :: Python :: 3.13
Classifier: Topic :: Utilities
Requires-Python: >=3.8
License-File: LICENSE
Requires-Dist: platformdirs
Requires-Dist: requests
Requires-Dist: rich
